{
  "accept": "akceptovat",
  "add": "přidat",
  "advanced": "pokročilý",
  "cancel": "zrušení",
  "change": "změna",
  "close": "zavřít",
  "continue": "pokračovat",
  "create": "vytvořit",
  "decline": "pokles",
  "delete": "vymazat",
  "deny": "odmítnout",
  "disable": "zakázat",
  "disabled": "zakázáno",
  "download": "stažení",
  "done": "Hotovo",
  "enable": "umožnit",
  "enabled": "povoleno",
  "info": "info",
  "no": "Ne",
  "noData": "žádná data",
  "off": "vypnuto",
  "ok": "OK",
  "on": "na",
  "reload": "Znovu načíst",
  "remove": "odstranit",
  "revert": "vrátit zpět",
  "save": "Uložit",
  "send": "poslat",
  "settings": "nastavení",
  "skip": "přeskočit",
  "share": "podíl",
  "undo": "vrátit",
  "upload": "nahrát",
  "viewMore": "ukázat více",
  "yes": "Ano"
}
