{
  "accept": "aceitar",
  "add": "adicionar",
  "advanced": "avançado",
  "cancel": "cancelar",
  "change": "mudar",
  "close": "fechar",
  "continue": "continuar",
  "create": "criar",
  "decline": "declínio",
  "delete": "excluir",
  "deny": "negar",
  "disable": "desabilitar",
  "disabled": "desabilitado",
  "download": "download",
  "done": "feito",
  "enable": "habilitar",
  "enabled": "habilitado",
  "info": "informações",
  "no": "não",
  "noData": "sem dados",
  "off": "desligado",
  "ok": "OK",
  "on": "sobre",
  "reload": "recarregar",
  "remove": "remover",
  "revert": "reverter",
  "save": "salvar",
  "send": "enviar",
  "settings": "configurações",
  "skip": "pular",
  "share": "compartilhar",
  "undo": "desfazer",
  "upload": "carregar",
  "viewMore": "Veja mais",
  "yes": "sim"
}
