{
  "yes": "ja",
  "no": "Nej",
  "ok": "OK",
  "cancel": "Avbryt",
  "save": "spara",
  "enable": "Gör det möjligt",
  "disable": "inaktivera",
  "send": "skicka",
  "change": "förändra",
  "reload": "ladda om",
  "revert": "återgå",
  "accept": "acceptera",
  "decline": "nedgång",
  "deny": "förneka",
  "download": "ladda ner",
  "upload": "ladda upp",
  "info": "info",
  "close": "stänga",
  "undo": "ångra",
  "share": "dela med sig",
  "viewMore": "visa mer",
  "advanced": "Avancerad",
  "continue": "Fortsätta",
  "add": "Lägg till",
  "delete": "radera",
  "remove": "avlägsna"
}
